date_validator/__init__.py
date_validator/core.py
pyspark_date_validator-0.2.5.dist-info/METADATA
pyspark_date_validator-0.2.5.dist-info/WHEEL
pyspark_date_validator-0.2.5.dist-info/top_level.txt
pyspark_date_validator-0.2.5.dist-info/RECORD
