Metadata-Version: 2.4
Name: pyspark_date_validator
Version: 0.2.5
Summary: A PySpark package to check missing dates in tables
Author-email: Natthakit Jeamprapakorn <natthakit.j@kasikornline.com>
License: MIT
Requires-Python: >=3.6
Requires-Dist: pyspark
